{"status":200,"msg":"OK","data":{"quest":{"id":"6391d90f4ed9512be67647df","normalized_name":"make-amends","name_en":"Make Amends","name_ko":"Make Amends","name_ja":"Make Amends","experience":0,"delay_max":0,"delay_min":0,"kappa_required":false,"min_player_level":33,"wiki_url":"https://escapefromtarkov.fandom.com/wiki/Make_Amends"},"trader":{"id":"5a7c2eca46aef81a7ca2145d","normalized_name":"mechanic","name_en":"Mechanic","name_ko":"메카닉","name_ja":"Mechanic","image":"https://assets.tarkov.dev/5a7c2eca46aef81a7ca2145d.webp"},"require_quests":[{"id":"6261482fa4eb80027c4f2e11","normalized_name":"make-amends-equipment","name_en":"Make Amends - Equipment","name_ko":"Make Amends - Equipment","name_ja":"Make Amends - Equipment"}],"next_quests":[{"id":"626148334149f1149b5b12ca","normalized_name":"make-amends-security","name_en":"Make Amends - Security","name_ko":"Make Amends - Security","name_ja":"Make Amends - Security"}],"objectives":[{"objective_id":"6391d9ba4b15ca31f76bc325","type":"findQuestItem","description_en":"Obtain the V3 Flash drive on Lighthouse","description_ko":"등대에서 V3 Flash drive를 획득하라","description_ja":"Lighthouse で V3 Flash drive を手に入れる","count":1,"found_in_raid":null,"items":[{"item_type":"questItem","item":{"id":"6331bb0d1aa9f42b804997a6","normalized_name":"secure-flash-drive-v3","name_en":"Secure Flash drive V3","name_ko":"Secure Flash drive V3","name_ja":"Secure Flash drive V3","image":"https://assets.tarkov.dev/6331bb0d1aa9f42b804997a6-grid-image.webp"}}],"required_keys":[],"maps":[],"live_map_points":[{"id":"6391d9ba4b15ca31f76bc325:05adc9afd0f6c74c","map_id":"5704e4dad2720bb55b8b4567","floor_id":"12","floor_no":1,"x":-69.882,"z":-654.61597,"y":2.4355,"details":[{"id":"6391d9ba4b15ca31f76bc325:05adc9afd0f6c74c:detail:1","description_en":"Obtain the V3 Flash drive on Lighthouse","description_ko":"등대에서 V3 Flash drive를 획득하라","description_ja":"Lighthouse で V3 Flash drive を手に入れる","image":null}],"map":{"id":"5704e4dad2720bb55b8b4567","normalized_name":"lighthouse","name_en":"Lighthouse","name_ko":"등대","name_ja":"Lighthouse"}},{"id":"6391d9ba4b15ca31f76bc325:0bd9ee6cafa4b6f2","map_id":"5704e4dad2720bb55b8b4567","floor_id":"12","floor_no":1,"x":-134.978,"z":-678.816,"y":2.879,"details":[{"id":"6391d9ba4b15ca31f76bc325:0bd9ee6cafa4b6f2:detail:1","description_en":"Obtain the V3 Flash drive on Lighthouse","description_ko":"등대에서 V3 Flash drive를 획득하라","description_ja":"Lighthouse で V3 Flash drive を手に入れる","image":null}],"map":{"id":"5704e4dad2720bb55b8b4567","normalized_name":"lighthouse","name_en":"Lighthouse","name_ko":"등대","name_ja":"Lighthouse"}},{"id":"6391d9ba4b15ca31f76bc325:1b140ccaddaa155c","map_id":"5704e4dad2720bb55b8b4567","floor_id":"12","floor_no":1,"x":-178.272,"z":-649.599,"y":5.8178,"details":[{"id":"6391d9ba4b15ca31f76bc325:1b140ccaddaa155c:detail:1","description_en":"Obtain the V3 Flash drive on Lighthouse","description_ko":"등대에서 V3 Flash drive를 획득하라","description_ja":"Lighthouse で V3 Flash drive を手に入れる","image":null}],"map":{"id":"5704e4dad2720bb55b8b4567","normalized_name":"lighthouse","name_en":"Lighthouse","name_ko":"등대","name_ja":"Lighthouse"}},{"id":"6391d9ba4b15ca31f76bc325:1f62bbc786bf0085","map_id":"5704e4dad2720bb55b8b4567","floor_id":"12","floor_no":1,"x":30.520096,"z":-646.7069,"y":9.1071,"details":[{"id":"6391d9ba4b15ca31f76bc325:1f62bbc786bf0085:detail:1","description_en":"Obtain the V3 Flash drive on Lighthouse","description_ko":"등대에서 V3 Flash drive를 획득하라","description_ja":"Lighthouse で V3 Flash drive を手に入れる","image":null}],"map":{"id":"5704e4dad2720bb55b8b4567","normalized_name":"lighthouse","name_en":"Lighthouse","name_ko":"등대","name_ja":"Lighthouse"}},{"id":"6391d9ba4b15ca31f76bc325:228e1583be3669c6","map_id":"5704e4dad2720bb55b8b4567","floor_id":"12","floor_no":1,"x":-100.754,"z":-491.3172,"y":1.0697,"details":[{"id":"6391d9ba4b15ca31f76bc325:228e1583be3669c6:detail:1","description_en":"Obtain the V3 Flash drive on Lighthouse","description_ko":"등대에서 V3 Flash drive를 획득하라","description_ja":"Lighthouse で V3 Flash drive を手に入れる","image":null}],"map":{"id":"5704e4dad2720bb55b8b4567","normalized_name":"lighthouse","name_en":"Lighthouse","name_ko":"등대","name_ja":"Lighthouse"}},{"id":"6391d9ba4b15ca31f76bc325:29a4bea1595420fd","map_id":"5704e4dad2720bb55b8b4567","floor_id":"12","floor_no":1,"x":-68.6482,"z":-697.1657,"y":2.978,"details":[{"id":"6391d9ba4b15ca31f76bc325:29a4bea1595420fd:detail:1","description_en":"Obtain the V3 Flash drive on Lighthouse","description_ko":"등대에서 V3 Flash drive를 획득하라","description_ja":"Lighthouse で V3 Flash drive を手に入れる","image":null}],"map":{"id":"5704e4dad2720bb55b8b4567","normalized_name":"lighthouse","name_en":"Lighthouse","name_ko":"등대","name_ja":"Lighthouse"}},{"id":"6391d9ba4b15ca31f76bc325:3119f479c005861d","map_id":"5704e4dad2720bb55b8b4567","floor_id":"12","floor_no":1,"x":27.950996,"z":-650.5705,"y":9.0999,"details":[{"id":"6391d9ba4b15ca31f76bc325:3119f479c005861d:detail:1","description_en":"Obtain the V3 Flash drive on Lighthouse","description_ko":"등대에서 V3 Flash drive를 획득하라","description_ja":"Lighthouse で V3 Flash drive を手に入れる","image":null}],"map":{"id":"5704e4dad2720bb55b8b4567","normalized_name":"lighthouse","name_en":"Lighthouse","name_ko":"등대","name_ja":"Lighthouse"}},{"id":"6391d9ba4b15ca31f76bc325:359af0b9dd5b06be","map_id":"5704e4dad2720bb55b8b4567","floor_id":"12","floor_no":1,"x":-197.6766,"z":-651.9562,"y":5.7923,"details":[{"id":"6391d9ba4b15ca31f76bc325:359af0b9dd5b06be:detail:1","description_en":"Obtain the V3 Flash drive on Lighthouse","description_ko":"등대에서 V3 Flash drive를 획득하라","description_ja":"Lighthouse で V3 Flash drive を手に入れる","image":null}],"map":{"id":"5704e4dad2720bb55b8b4567","normalized_name":"lighthouse","name_en":"Lighthouse","name_ko":"등대","name_ja":"Lighthouse"}},{"id":"6391d9ba4b15ca31f76bc325:40eb8721cc448634","map_id":"5704e4dad2720bb55b8b4567","floor_id":"12","floor_no":1,"x":-122.483,"z":-733.80457,"y":5.4249,"details":[{"id":"6391d9ba4b15ca31f76bc325:40eb8721cc448634:detail:1","description_en":"Obtain the V3 Flash drive on Lighthouse","description_ko":"등대에서 V3 Flash drive를 획득하라","description_ja":"Lighthouse で V3 Flash drive を手に入れる","image":null}],"map":{"id":"5704e4dad2720bb55b8b4567","normalized_name":"lighthouse","name_en":"Lighthouse","name_ko":"등대","name_ja":"Lighthouse"}},{"id":"6391d9ba4b15ca31f76bc325:4c3056801879bfed","map_id":"5704e4dad2720bb55b8b4567","floor_id":"12","floor_no":1,"x":-171.334,"z":-633.393,"y":9.2309,"details":[{"id":"6391d9ba4b15ca31f76bc325:4c3056801879bfed:detail:1","description_en":"Obtain the V3 Flash drive on Lighthouse","description_ko":"등대에서 V3 Flash drive를 획득하라","description_ja":"Lighthouse で V3 Flash drive を手に入れる","image":null}],"map":{"id":"5704e4dad2720bb55b8b4567","normalized_name":"lighthouse","name_en":"Lighthouse","name_ko":"등대","name_ja":"Lighthouse"}},{"id":"6391d9ba4b15ca31f76bc325:4c63593e209084d7","map_id":"5704e4dad2720bb55b8b4567","floor_id":"12","floor_no":1,"x":-134.9648,"z":-678.8499,"y":2.879,"details":[{"id":"6391d9ba4b15ca31f76bc325:4c63593e209084d7:detail:1","description_en":"Obtain the V3 Flash drive on Lighthouse","description_ko":"등대에서 V3 Flash drive를 획득하라","description_ja":"Lighthouse で V3 Flash drive を手に入れる","image":null}],"map":{"id":"5704e4dad2720bb55b8b4567","normalized_name":"lighthouse","name_en":"Lighthouse","name_ko":"등대","name_ja":"Lighthouse"}},{"id":"6391d9ba4b15ca31f76bc325:6df7ffa71cc34bab","map_id":"5704e4dad2720bb55b8b4567","floor_id":"12","floor_no":1,"x":-28.763802,"z":-525.2898,"y":2.8203,"details":[{"id":"6391d9ba4b15ca31f76bc325:6df7ffa71cc34bab:detail:1","description_en":"Obtain the V3 Flash drive on Lighthouse","description_ko":"등대에서 V3 Flash drive를 획득하라","description_ja":"Lighthouse で V3 Flash drive を手に入れる","image":null}],"map":{"id":"5704e4dad2720bb55b8b4567","normalized_name":"lighthouse","name_en":"Lighthouse","name_ko":"등대","name_ja":"Lighthouse"}},{"id":"6391d9ba4b15ca31f76bc325:73e83a1cf41f36c5","map_id":"5704e4dad2720bb55b8b4567","floor_id":"12","floor_no":1,"x":-100.336,"z":-491.862,"y":1.0239,"details":[{"id":"6391d9ba4b15ca31f76bc325:73e83a1cf41f36c5:detail:1","description_en":"Obtain the V3 Flash drive on Lighthouse","description_ko":"등대에서 V3 Flash drive를 획득하라","description_ja":"Lighthouse で V3 Flash drive を手に入れる","image":null}],"map":{"id":"5704e4dad2720bb55b8b4567","normalized_name":"lighthouse","name_en":"Lighthouse","name_ko":"등대","name_ja":"Lighthouse"}},{"id":"6391d9ba4b15ca31f76bc325:92779541d6936070","map_id":"5704e4dad2720bb55b8b4567","floor_id":"12","floor_no":1,"x":-65.779,"z":-734.927,"y":5.8256,"details":[{"id":"6391d9ba4b15ca31f76bc325:92779541d6936070:detail:1","description_en":"Obtain the V3 Flash drive on Lighthouse","description_ko":"등대에서 V3 Flash drive를 획득하라","description_ja":"Lighthouse で V3 Flash drive を手に入れる","image":null}],"map":{"id":"5704e4dad2720bb55b8b4567","normalized_name":"lighthouse","name_en":"Lighthouse","name_ko":"등대","name_ja":"Lighthouse"}},{"id":"6391d9ba4b15ca31f76bc325:96420997554626ac","map_id":"5704e4dad2720bb55b8b4567","floor_id":"12","floor_no":1,"x":-61.8229,"z":-689.448,"y":2.7611,"details":[{"id":"6391d9ba4b15ca31f76bc325:96420997554626ac:detail:1","description_en":"Obtain the V3 Flash drive on Lighthouse","description_ko":"등대에서 V3 Flash drive를 획득하라","description_ja":"Lighthouse で V3 Flash drive を手に入れる","image":null}],"map":{"id":"5704e4dad2720bb55b8b4567","normalized_name":"lighthouse","name_en":"Lighthouse","name_ko":"등대","name_ja":"Lighthouse"}},{"id":"6391d9ba4b15ca31f76bc325:990533df02d3d97d","map_id":"5704e4dad2720bb55b8b4567","floor_id":"12","floor_no":1,"x":-133.4922,"z":-497.9937,"y":2.8779,"details":[{"id":"6391d9ba4b15ca31f76bc325:990533df02d3d97d:detail:1","description_en":"Obtain the V3 Flash drive on Lighthouse","description_ko":"등대에서 V3 Flash drive를 획득하라","description_ja":"Lighthouse で V3 Flash drive を手に入れる","image":null}],"map":{"id":"5704e4dad2720bb55b8b4567","normalized_name":"lighthouse","name_en":"Lighthouse","name_ko":"등대","name_ja":"Lighthouse"}},{"id":"6391d9ba4b15ca31f76bc325:a18ab534e26033cd","map_id":"5704e4dad2720bb55b8b4567","floor_id":"12","floor_no":1,"x":-114.446,"z":-731.515,"y":9.1008,"details":[{"id":"6391d9ba4b15ca31f76bc325:a18ab534e26033cd:detail:1","description_en":"Obtain the V3 Flash drive on Lighthouse","description_ko":"등대에서 V3 Flash drive를 획득하라","description_ja":"Lighthouse で V3 Flash drive を手に入れる","image":null}],"map":{"id":"5704e4dad2720bb55b8b4567","normalized_name":"lighthouse","name_en":"Lighthouse","name_ko":"등대","name_ja":"Lighthouse"}},{"id":"6391d9ba4b15ca31f76bc325:a8161d1ce298a9e9","map_id":"5704e4dad2720bb55b8b4567","floor_id":"12","floor_no":1,"x":-139.22,"z":-686.048,"y":2.4206,"details":[{"id":"6391d9ba4b15ca31f76bc325:a8161d1ce298a9e9:detail:1","description_en":"Obtain the V3 Flash drive on Lighthouse","description_ko":"등대에서 V3 Flash drive를 획득하라","description_ja":"Lighthouse で V3 Flash drive を手に入れる","image":null}],"map":{"id":"5704e4dad2720bb55b8b4567","normalized_name":"lighthouse","name_en":"Lighthouse","name_ko":"등대","name_ja":"Lighthouse"}},{"id":"6391d9ba4b15ca31f76bc325:b0f948732f4782bd","map_id":"5704e4dad2720bb55b8b4567","floor_id":"12","floor_no":1,"x":0.19200134,"z":-598.199,"y":2.8773,"details":[{"id":"6391d9ba4b15ca31f76bc325:b0f948732f4782bd:detail:1","description_en":"Obtain the V3 Flash drive on Lighthouse","description_ko":"등대에서 V3 Flash drive를 획득하라","description_ja":"Lighthouse で V3 Flash drive を手に入れる","image":null}],"map":{"id":"5704e4dad2720bb55b8b4567","normalized_name":"lighthouse","name_en":"Lighthouse","name_ko":"등대","name_ja":"Lighthouse"}},{"id":"6391d9ba4b15ca31f76bc325:b37c59909f61c7b6","map_id":"5704e4dad2720bb55b8b4567","floor_id":"12","floor_no":1,"x":-63.175003,"z":-627.414,"y":5.2796,"details":[{"id":"6391d9ba4b15ca31f76bc325:b37c59909f61c7b6:detail:1","description_en":"Obtain the V3 Flash drive on Lighthouse","description_ko":"등대에서 V3 Flash drive를 획득하라","description_ja":"Lighthouse で V3 Flash drive を手に入れる","image":null}],"map":{"id":"5704e4dad2720bb55b8b4567","normalized_name":"lighthouse","name_en":"Lighthouse","name_ko":"등대","name_ja":"Lighthouse"}},{"id":"6391d9ba4b15ca31f76bc325:eeabf45f81056051","map_id":"5704e4dad2720bb55b8b4567","floor_id":"12","floor_no":1,"x":-46.718002,"z":-519.991,"y":8.1166,"details":[{"id":"6391d9ba4b15ca31f76bc325:eeabf45f81056051:detail:1","description_en":"Obtain the V3 Flash drive on Lighthouse","description_ko":"등대에서 V3 Flash drive를 획득하라","description_ja":"Lighthouse で V3 Flash drive を手に入れる","image":null}],"map":{"id":"5704e4dad2720bb55b8b4567","normalized_name":"lighthouse","name_en":"Lighthouse","name_ko":"등대","name_ja":"Lighthouse"}},{"id":"6391d9ba4b15ca31f76bc325:efb7fae2fb088fe9","map_id":"5704e4dad2720bb55b8b4567","floor_id":"12","floor_no":1,"x":-100.294,"z":-492.171,"y":1.024,"details":[{"id":"6391d9ba4b15ca31f76bc325:efb7fae2fb088fe9:detail:1","description_en":"Obtain the V3 Flash drive on Lighthouse","description_ko":"등대에서 V3 Flash drive를 획득하라","description_ja":"Lighthouse で V3 Flash drive を手に入れる","image":null}],"map":{"id":"5704e4dad2720bb55b8b4567","normalized_name":"lighthouse","name_en":"Lighthouse","name_ko":"등대","name_ja":"Lighthouse"}},{"id":"6391d9ba4b15ca31f76bc325:fd4e05a84fe55b74","map_id":"5704e4dad2720bb55b8b4567","floor_id":"12","floor_no":1,"x":50.545998,"z":-649.859,"y":5.927,"details":[{"id":"6391d9ba4b15ca31f76bc325:fd4e05a84fe55b74:detail:1","description_en":"Obtain the V3 Flash drive on Lighthouse","description_ko":"등대에서 V3 Flash drive를 획득하라","description_ja":"Lighthouse で V3 Flash drive を手に入れる","image":null}],"map":{"id":"5704e4dad2720bb55b8b4567","normalized_name":"lighthouse","name_en":"Lighthouse","name_ko":"등대","name_ja":"Lighthouse"}}]},{"objective_id":"6391d9e7ee79ee703e3012e5","type":"findItem","description_en":"Reflash the Radio transmitter","description_ko":"라디오 송신기를 다시 플래시하라","description_ja":"Radio transmitter を再フラッシュする","count":1,"found_in_raid":false,"items":[{"item_type":"item","item":{"id":"62e910aaf957f2915e0a5e36","normalized_name":"digital-secure-dsp-radio-transmitter","name_en":"Digital secure DSP radio transmitter","name_ko":"Digital secure DSP radio transmitter","name_ja":"暗号化機能付 DSP 無線送信機","image":"https://assets.tarkov.dev/62e910aaf957f2915e0a5e36-grid-image.webp"}}],"required_keys":[],"maps":[]},{"objective_id":"6391d9fd8ba6894d155e77db","type":"giveQuestItem","description_en":"Hand over the flash drive","description_ko":"플래시 드라이브를 전달하라","description_ja":"Flash drive を渡す","count":1,"found_in_raid":null,"items":[{"item_type":"questItem","item":{"id":"6331bb0d1aa9f42b804997a6","normalized_name":"secure-flash-drive-v3","name_en":"Secure Flash drive V3","name_ko":"Secure Flash drive V3","name_ja":"Secure Flash drive V3","image":"https://assets.tarkov.dev/6331bb0d1aa9f42b804997a6-grid-image.webp"}}],"required_keys":[],"maps":[]},{"objective_id":"63ab6a89e842787ad2135719","type":"visit","description_en":"Visit the Lighthouse building","description_ko":"등대 건물을 방문하라","description_ja":"Lighthouse 建物を訪れる","count":null,"found_in_raid":null,"items":[],"required_keys":[],"maps":[],"live_map_points":[{"id":"63ab6a89e842787ad2135719:c760f5a06a48ae8f","map_id":"5704e4dad2720bb55b8b4567","floor_id":"12","floor_no":1,"x":442.2326,"z":460.690674,"y":24.1148987,"details":[{"id":"63ab6a89e842787ad2135719:c760f5a06a48ae8f:detail:1","description_en":"Visit the Lighthouse building","description_ko":"등대 건물을 방문하라","description_ja":"Lighthouse 建物を訪れる","image":null}],"map":{"id":"5704e4dad2720bb55b8b4567","normalized_name":"lighthouse","name_en":"Lighthouse","name_ko":"등대","name_ja":"Lighthouse"}}]}],"finish_rewards":{"skill_level_reward":[],"trader_standing":[{"standing":0.01,"trader":{"id":"5a7c2eca46aef81a7ca2145d","normalized_name":"mechanic","name_en":"Mechanic","name_ko":"메카닉","name_ja":"Mechanic","image":"https://assets.tarkov.dev/5a7c2eca46aef81a7ca2145d.webp"}}],"offer_unlock":[],"items":[],"craft_unlock":[]}}}
